igem_wikisync/__init__.py
igem_wikisync/__main__.py
igem_wikisync/browser.py
igem_wikisync/cli.py
igem_wikisync/files.py
igem_wikisync/logger.py
igem_wikisync/parsers.py
igem_wikisync/path.py
igem_wikisync/wikisync.py
igem_wikisync-1.0.0.dist-info/AUTHORS.rst
igem_wikisync-1.0.0.dist-info/LICENSE
igem_wikisync-1.0.0.dist-info/METADATA
igem_wikisync-1.0.0.dist-info/WHEEL
igem_wikisync-1.0.0.dist-info/entry_points.txt
igem_wikisync-1.0.0.dist-info/top_level.txt
igem_wikisync-1.0.0.dist-info/RECORD
