Metadata-Version: 2.1
Name: igem-wikisync
Version: 1.0.0
Summary: Continuous integration and deployment for iGEM Wikis.
Home-page: https://github.com/igembitsgoa/igem-wikisync
Author: Pranav Ballaney
Author-email: ballaneypranav@gmail.com
License: MIT
Project-URL: Documentation, https://igem-wikisync.readthedocs.io/
Project-URL: Changelog, https://igem-wikisync.readthedocs.io/en/latest/changelog.html
Project-URL: Issue Tracker, https://github.com/igembitsgoa/igem-wikisync/issues
Platform: UNKNOWN
Classifier: Development Status :: 5 - Production/Stable
Classifier: Intended Audience :: Developers
Classifier: License :: OSI Approved :: MIT License
Classifier: Operating System :: Unix
Classifier: Operating System :: POSIX
Classifier: Operating System :: Microsoft :: Windows
Classifier: Programming Language :: Python
Classifier: Programming Language :: Python :: 3.6
Classifier: Programming Language :: Python :: 3.7
Classifier: Programming Language :: Python :: 3.8
Classifier: Topic :: Utilities
Requires-Python: >=3.6
Requires-Dist: html5lib (>=1.1)
Requires-Dist: mechanicalsoup (>=0.12.0)
Requires-Dist: pyopenssl (>=19.1.0)
Requires-Dist: pyyaml (>=5.3.1)
